[
  {
    "id": "2dad2bbd48f9",
    "category": "oki",
    "topic": "ラッシュ後の連携による崩し",
    "content": "ラッシュ中足をガードさせた後は、ヒットかガードかを判断し、ヒット時はコンボへ、ガード時は択を仕掛けます。ガードさせた後の選択肢としては、再度ラッシュ中足、投げ、またはシミーがあります。相手が後ろ下がり、バクステ、暴れ、バックジャンプをしてくる場合は、ラッシュ中足 > 立ち弱K > 弱一文字まで繋げます。投げ抜けを誘う場合は、ラッシュ中足の後に少し待って投げを入れることで、相手の投げ抜けを誘うことができます。（ただし、最速投げだとガード構築の都合上スカる場合があるため注意）。この連携を繰り返すことで、相手を崩すことができます。",
    "characters": [
      "kimberly"
    ],
    "matchup": null,
    "situation": null,
    "source_video_id": "S-YYjuSW0LA",
    "source_channel": "いおりチャンネル【スト6講座と対戦動画投稿】",
    "source_video_title": "【スト６】１０分で使えるキンバリー講座！！簡単で強いセットプレイも紹介！！【Street Fighter 6】",
    "source_timestamp": "07:09",
    "source_quote": "ラッシュ後連携。\nまずはヒットかガードか判断してコンボにつなげるか択を仕掛けるか判断したい。\n後ろ下がり、バクステ、暴れ、バックジャンプ > ラッシュ中足 > 立ち弱K > 弱一文字or大武神旋風脚\n投げ抜け > ラッシュ中足 > シミー\nガード > ラッシュ中足 > ちょい待って投げ 最速投げだとスカる",
    "confidence": 1.0,
    "channel_trust": 0.8,
    "frame_data_conflicts": [],
    "extracted_at": "2026-03-30T02:42:12.293497",
    "game_version": "2",
    "video_upload_date": "",
    "referenced_moves": [
      "101",
      "109"
    ],
    "staleness_status": "current",
    "staleness_reason": "",
    "last_validated_version": ""
  },
  {
    "id": "6d3ddbab9b54",
    "category": "oki",
    "topic": "爆竹セットプレイ（疾駆け>影すくい後）",
    "content": "疾駆け>影すくいでダウンを奪った後の爆竹セットプレイです。最速で爆竹を設置し、\n1. 相手がガードするなら投げ。\n2. 相手が暴れやバクステ、ジャンプなどをするなら屈弱P > 屈弱P > 屈弱P > 弱一文字（SA3）でフルコンボ。\n3. 相手がシミーをするならバックステップ > 立ち中K > 弱一文字。\n4. 相手がシミーや一部無敵技を警戒してくるなら前ジャンプ > 肘 > 屈弱P。\n5. 直で中段崩しを狙うなら後ろ強K > 屈弱P > 弱一文字。",
    "characters": [
      "kimberly"
    ],
    "matchup": null,
    "situation": "爆竹設置後",
    "source_video_id": "S-YYjuSW0LA",
    "source_channel": "いおりチャンネル【スト6講座と対戦動画投稿】",
    "source_video_title": "【スト６】１０分で使えるキンバリー講座！！簡単で強いセットプレイも紹介！！【Street Fighter 6】",
    "source_timestamp": "09:42",
    "source_quote": "爆竹セットプレイ 疾駆け>影すくいメ\n最速設置 > 投げ (相手がガードのときの選択肢)\n爆発後は同じ\n2369で出すOD空投げ > 前大K > ジャンプ中P > 弱一文字 (SA3)\n最速設置 > 屈弱P > 屈弱P > 屈弱P > 弱一文字 (暴れやバクステ、ジャンプなどに勝つ)\n爆発後は同じ\n2369で出すOD空投げ > 前大K > ジャンプ中P > 弱一文字 (SA3)\n最速設置 > バクステ > 立ち中K > 弱一文字 (シミー)\n爆発後は同じ\n2369で出すOD空投げ > 前大K > ジャンプ中P > 弱一文字 (SA3)\n最速設置 > 前ジャンプ > 肘 > 屈弱P (シミーとか一部無敵警戒)\n爆発後は同じ\n2369で出すOD空投げ > 前大K > ジャンプ中P > 弱一文字 (SA3)\n最速設置 > 屈弱P > 屈弱P > 後ろ強K (中段崩し)\n爆発後は同じ\n2369で出すOD空投げ > 前大K > ジャンプ中P > 弱一文字 (SA3)\n最速設置 > 後ろ強K > 屈弱P > 弱一文字 (直で中段崩し)\n爆発後は同じ\n2369で出すOD空投げ > 前大K > ジャンプ中P > 弱一文字 (SA3)",
    "confidence": 1.0,
    "channel_trust": 0.8,
    "frame_data_conflicts": [],
    "extracted_at": "2026-03-30T02:42:12.293497",
    "game_version": "2",
    "video_upload_date": "",
    "referenced_moves": [
      "103",
      "105",
      "114",
      "306",
      "312",
      "None"
    ],
    "staleness_status": "current",
    "staleness_reason": "",
    "last_validated_version": ""
  },
  {
    "id": "a8096132d8a2",
    "category": "oki",
    "topic": "空中乱舞彩蹴手裏剣の設置タイミング",
    "content": "キンバリーの空中乱舞彩蹴手裏剣（空中下下P）は、弱中版または中強版を使用すると手裏剣が2つ設置できる。弱強版は前バージョンと同様にほぼ同時に爆発するが、弱中版または中強版は爆発タイミングが遅くなるため、これを利用してセットプレイを組むと良い。ストックは体力ゲージの下に表示される。",
    "characters": [
      "kimberly"
    ],
    "matchup": null,
    "situation": "起き攻め時、または手裏剣を設置したい時",
    "source_video_id": "FipZdQzs-qI",
    "source_channel": "ストーム久保",
    "source_video_title": "ほぼ確定で体力を5割減らすキンバリーの新起き攻めの強制力が強すぎて困惑するストーム久保【スト6】",
    "source_timestamp": "00:20",
    "source_quote": "乱舞彩蹴手裏剣 体力ゲージの下にストック」「使って設置する」「下下Pの弱中強によって置く位置が変わる技」「弱中とか同上すると2個設置できます」「弱強で置くと前バージョンと一緒でほぼ同じタイミングで爆発する」「弱中と中強で設置すると爆発するタイミングが遅くなります",
    "confidence": 1.0,
    "channel_trust": 0.8,
    "frame_data_conflicts": [],
    "extracted_at": "2026-03-30T05:37:00.506276",
    "game_version": "2",
    "video_upload_date": "",
    "referenced_moves": [],
    "staleness_status": "current",
    "staleness_reason": "",
    "last_validated_version": ""
  },
  {
    "id": "872063fa7b1e",
    "category": "oki",
    "topic": "中P強Pからのセットプレイ",
    "content": "キンバリーは中P→強Pのターゲットコンボの後、派生移動スラッシュで手裏剣を設置すると、+3Fの有利フレームが得られる。これにより、その場から投げと立ち中Pが埋まる連携となる。",
    "characters": [
      "kimberly"
    ],
    "matchup": null,
    "situation": "相手のダウン時",
    "source_video_id": "FipZdQzs-qI",
    "source_channel": "ストーム久保",
    "source_video_title": "ほぼ確定で体力を5割減らすキンバリーの新起き攻めの強制力が強すぎて困惑するストーム久保【スト6】",
    "source_timestamp": "01:03",
    "source_quote": "中パン強パンターゲットコンボハイがけすら設置がプラス3でその場から投げと中パンが埋まってる",
    "confidence": 1.0,
    "channel_trust": 0.8,
    "frame_data_conflicts": [],
    "extracted_at": "2026-03-30T05:37:00.506276",
    "game_version": "2",
    "video_upload_date": "",
    "referenced_moves": [
      "102"
    ],
    "staleness_status": "current",
    "staleness_reason": "",
    "last_validated_version": ""
  },
  {
    "id": "eacf842c1399",
    "category": "oki",
    "topic": "投げ後の起き攻め連携",
    "content": "キンバリーの投げ後、前ステップから派生移動を出し、弱版乱舞彩蹴手裏剣を設置することで、手裏剣を良い高さに設置できる連携。",
    "characters": [
      "kimberly"
    ],
    "matchup": null,
    "situation": "投げ後の起き攻め時",
    "source_video_id": "FipZdQzs-qI",
    "source_channel": "ストーム久保",
    "source_video_title": "ほぼ確定で体力を5割減らすキンバリーの新起き攻めの強制力が強すぎて困惑するストーム久保【スト6】",
    "source_timestamp": "01:14",
    "source_quote": "投げた時は前してハイがけジャッキ発生でいい高さ",
    "confidence": 1.0,
    "channel_trust": 0.8,
    "frame_data_conflicts": [],
    "extracted_at": "2026-03-30T05:37:00.506276",
    "game_version": "2",
    "video_upload_date": "",
    "referenced_moves": [],
    "staleness_status": "current",
    "staleness_reason": "",
    "last_validated_version": ""
  },
  {
    "id": "dc205a99a7ee",
    "category": "oki",
    "topic": "投げ後の手裏剣設置の工夫",
    "content": "キンバリーの投げから手裏剣設置を行う際、前ステップを挟んでから出すことで、より良い連携に繋がる可能性がある。",
    "characters": [
      "kimberly"
    ],
    "matchup": null,
    "situation": "投げ後の起き攻めで手裏剣を設置する時",
    "source_video_id": "FipZdQzs-qI",
    "source_channel": "ストーム久保",
    "source_video_title": "ほぼ確定で体力を5割減らすキンバリーの新起き攻めの強制力が強すぎて困惑するストーム久保【スト6】",
    "source_timestamp": "04:20",
    "source_quote": "前ステでいいんですか？」「前ステ同派生でいいのか",
    "confidence": 1.0,
    "channel_trust": 0.8,
    "frame_data_conflicts": [],
    "extracted_at": "2026-03-30T05:37:00.506276",
    "game_version": "2",
    "video_upload_date": "",
    "referenced_moves": [],
    "staleness_status": "current",
    "staleness_reason": "",
    "last_validated_version": ""
  },
  {
    "id": "326ba3a8f4eb",
    "category": "oki",
    "topic": "投げからの手裏剣設置連携",
    "content": "キンバリーは投げ後、立ち大Pから立ち中Kに繋ぎ、空中乱舞彩蹴手裏剣の弱中版で手裏剣を設置する連携が強力。",
    "characters": [
      "kimberly"
    ],
    "matchup": null,
    "situation": "投げ後の起き攻め時",
    "source_video_id": "FipZdQzs-qI",
    "source_channel": "ストーム久保",
    "source_video_title": "ほぼ確定で体力を5割減らすキンバリーの新起き攻めの強制力が強すぎて困惑するストーム久保【スト6】",
    "source_timestamp": "08:00",
    "source_quote": "投げ大p3中k弱中設置」「っていうことだよね、多分",
    "confidence": 1.0,
    "channel_trust": 0.8,
    "frame_data_conflicts": [],
    "extracted_at": "2026-03-30T05:37:00.506276",
    "game_version": "2",
    "video_upload_date": "",
    "referenced_moves": [
      "103"
    ],
    "staleness_status": "current",
    "staleness_reason": "",
    "last_validated_version": ""
  },
  {
    "id": "9a6fb4cf79b0",
    "category": "oki",
    "topic": "疾駆け下段派生後の起き攻め",
    "content": "疾駆けからの下段派生（影すくい）をヒットさせた後は、相手がダウンするため、起き攻めに移行できます。低姿勢であるため、相手の弾などを潜りつつ起き攻めを仕掛けられます。",
    "characters": [
      "kimberly"
    ],
    "matchup": null,
    "situation": "起き攻め（疾駆け下段派生後）",
    "source_video_id": "9kshXTikTLM",
    "source_channel": "べーやんの部屋【ゆっくり解説チャンネル】",
    "source_video_title": "【それっぽく動かすキンバリー】順番に覚えれば動画のようなセットプレイができる！ガン攻め好きにおすすめのキンバリー初心者向け解説講座【ストリートファイター6】【スト6】",
    "source_timestamp": "03:32",
    "source_quote": "ヒット時はダウンがとれ起き攻めに行くことができ低姿勢なので弾などもくぐる事ができます。",
    "confidence": 1.0,
    "channel_trust": 0.3,
    "frame_data_conflicts": [],
    "extracted_at": "2026-03-30T07:55:03.614751",
    "game_version": "2",
    "video_upload_date": "",
    "referenced_moves": [
      "306",
      "312"
    ],
    "staleness_status": "current",
    "staleness_reason": "",
    "last_validated_version": ""
  },
  {
    "id": "c7d36a4fe9cb",
    "category": "oki",
    "topic": "影すくいガード後の首狩り派生",
    "content": "相手が影すくい（下段派生）を警戒してガードするようになったら、首狩り（中段派生）を織り交ぜましょう。首狩りはしゃがみガードできないため、相手のガードを崩すのに有効です。",
    "characters": [
      "kimberly"
    ],
    "matchup": null,
    "situation": "相手が下段派生をガードしている状況",
    "source_video_id": "9kshXTikTLM",
    "source_channel": "べーやんの部屋【ゆっくり解説チャンネル】",
    "source_video_title": "【それっぽく動かすキンバリー】順番に覚えれば動画のようなセットプレイができる！ガン攻め好きにおすすめのキンバリー初心者向け解説講座【ストリートファイター6】【スト6】",
    "source_timestamp": "03:51",
    "source_quote": "この技を警戒してガードをするようになった相手にはガードさせてキンバリーが有利な同派生や影すくいと対になるしゃがみガードできない首狩りに派生するのも良いでしょう。",
    "confidence": 1.0,
    "channel_trust": 0.3,
    "frame_data_conflicts": [],
    "extracted_at": "2026-03-30T07:55:03.614751",
    "game_version": "2",
    "video_upload_date": "",
    "referenced_moves": [
      "312",
      "314"
    ],
    "staleness_status": "current",
    "staleness_reason": "",
    "last_validated_version": ""
  },
  {
    "id": "b28b96471c90",
    "category": "oki",
    "topic": "自動派生からのコマ投げ（武神イズナ落とし）",
    "content": "疾駆けが追加入力なしで相手に到達して自動で孤空に派生した場合、地上の相手を投げる武神イズナ落とし（コマ投げ派生）に繋げられます。",
    "characters": [
      "kimberly"
    ],
    "matchup": null,
    "situation": "起き攻め（疾駆け自動派生後）",
    "source_video_id": "9kshXTikTLM",
    "source_channel": "べーやんの部屋【ゆっくり解説チャンネル】",
    "source_video_title": "【それっぽく動かすキンバリー】順番に覚えれば動画のようなセットプレイができる！ガン攻め好きにおすすめのキンバリー初心者向け解説講座【ストリートファイター6】【スト6】",
    "source_timestamp": "04:14",
    "source_quote": "この技からは地上の相手を投げる事ができる武神イズナ落としとそれをよけようとしたり迎撃しようとした相手にあたる武神斬影脚にそれぞれ派生することができます。",
    "confidence": 1.0,
    "channel_trust": 0.3,
    "frame_data_conflicts": [],
    "extracted_at": "2026-03-30T07:55:03.614751",
    "game_version": "2",
    "video_upload_date": "",
    "referenced_moves": [
      "306",
      "318"
    ],
    "staleness_status": "current",
    "staleness_reason": "",
    "last_validated_version": ""
  },
  {
    "id": "c215804de4fa",
    "category": "oki",
    "topic": "投げ後の起き攻め（中Pタゲコン）",
    "content": "投げ後の起き攻めとして、モダン操作のキンバリーは中Pタゲコンから疾駆け下段派生に繋げるのが強力です。相手の起き上がりに重ねてヒットするとコンボになります。ヒット時は強アシコンを連打して追撃し、再度起き攻めに持っていきましょう。この攻めを2回ほど通せば相手を画面端に追い詰めることができます。",
    "characters": [
      "kimberly"
    ],
    "matchup": null,
    "situation": "投げ後の起き攻め",
    "source_video_id": "9kshXTikTLM",
    "source_channel": "べーやんの部屋【ゆっくり解説チャンネル】",
    "source_video_title": "【それっぽく動かすキンバリー】順番に覚えれば動画のようなセットプレイができる！ガン攻め好きにおすすめのキンバリー初心者向け解説講座【ストリートファイター6】【スト6】",
    "source_timestamp": "06:31",
    "source_quote": "まずはモダンの強アシコンである中Pタゲコン疾駆け下段締め後の起き攻めです。うまく重ねられるとこれを潰してchをとることができるのでヒット時は強アシコンを連打して再度起き攻めに持っていきましょう。大体2回くらいこの攻めを通すと相手を画面端に追い詰めることができます。",
    "confidence": 1.0,
    "channel_trust": 0.3,
    "frame_data_conflicts": [],
    "extracted_at": "2026-03-30T07:55:03.614751",
    "game_version": "2",
    "video_upload_date": "",
    "referenced_moves": [
      "306"
    ],
    "staleness_status": "current",
    "staleness_reason": "",
    "last_validated_version": ""
  },
  {
    "id": "cc22190d69f8",
    "category": "oki",
    "topic": "画面端での投げ柔道",
    "content": "キンバリーは画面端で歩きからの投げを繰り返す「柔道」が可能です。これは疾駆け下段派生後の起き攻めと同様の考え方で、投げのタイミングをうまく合わせれば相手の暴れを潰して投げられます。余裕があればセットで練習すると良いでしょう。",
    "characters": [
      "kimberly"
    ],
    "matchup": null,
    "situation": "画面端での起き攻め",
    "source_video_id": "9kshXTikTLM",
    "source_channel": "べーやんの部屋【ゆっくり解説チャンネル】",
    "source_video_title": "【それっぽく動かすキンバリー】順番に覚えれば動画のようなセットプレイができる！ガン攻め好きにおすすめのキンバリー初心者向け解説講座【ストリートファイター6】【スト6】",
    "source_timestamp": "07:48",
    "source_quote": "キンバリーは端の場合歩くことで投げをループさせることができる通称柔道をつかうことができるキャラです。ステップではなく歩きではありますが基本的には下段派生〆の時と変わりません。投げもタイミングよくやれば相手の暴れを潰して投げる事が可能なので余裕があればセットで練習するとよいでしょう。",
    "confidence": 1.0,
    "channel_trust": 0.3,
    "frame_data_conflicts": [],
    "extracted_at": "2026-03-30T07:55:03.614751",
    "game_version": "2",
    "video_upload_date": "",
    "referenced_moves": [
      "306"
    ],
    "staleness_status": "current",
    "staleness_reason": "",
    "last_validated_version": ""
  },
  {
    "id": "2f3ab6325ee9",
    "category": "oki",
    "topic": "強Kガード後の当て投げと読み合い",
    "content": "強Kがガードされた後、相手が4F技で暴れた場合は相打ちになります。この相打ちを確認できれば中Pや中Kで追撃可能です。モダン操作の場合は、相打ち確認後にAutoボタンを押しながら中アシコンを打つのが簡単です。この連携ができるようになると、相手は中Pまでガードするようになるため、強Kガード後に歩いて投げをする「当て投げ」が通るようになります。",
    "characters": [
      "kimberly"
    ],
    "matchup": null,
    "situation": "強Kガード後",
    "source_video_id": "9kshXTikTLM",
    "source_channel": "べーやんの部屋【ゆっくり解説チャンネル】",
    "source_video_title": "【それっぽく動かすキンバリー】順番に覚えれば動画のようなセットプレイができる！ガン攻め好きにおすすめのキンバリー初心者向け解説講座【ストリートファイター6】【スト6】",
    "source_timestamp": "08:09",
    "source_quote": "この連携は相手が4Fの技で暴れた場合相打ちしてしまいますがこれを確定できた場合中Pや中Kで追撃することが可能です。モダンの場合Autoボタンを押しているので相打ち確認だけして中アシコンを打つのが一番楽な方法になります。これができるようになると相手は中Pまでガードしてから何かするようにになるので強Kのガード後歩いて投げる通称当て投げが通るようになります。",
    "confidence": 1.0,
    "channel_trust": 0.3,
    "frame_data_conflicts": [],
    "extracted_at": "2026-03-30T07:55:03.614751",
    "game_version": "2",
    "video_upload_date": "",
    "referenced_moves": [],
    "staleness_status": "current",
    "staleness_reason": "",
    "last_validated_version": ""
  },
  {
    "id": "10cd62895031",
    "category": "oki",
    "topic": "手裏剣設置からの投げ起き攻め",
    "content": "画面端で強アシコンから疾駆け下段派生まで繋げた後、22強Pで手裏剣を設置します。設置後は、投げを連打することで最速で投げに移行でき、コンボに繋げることが可能です。ただし、最速投げは有利フレームが長くなるため、投げたい場合は少し遅らせて入力する注意が必要です。",
    "characters": [
      "kimberly"
    ],
    "matchup": null,
    "situation": "画面端、手裏剣設置後",
    "source_video_id": "9kshXTikTLM",
    "source_channel": "べーやんの部屋【ゆっくり解説チャンネル】",
    "source_video_title": "【それっぽく動かすキンバリー】順番に覚えれば動画のようなセットプレイができる！ガン攻め好きにおすすめのキンバリー初心者向け解説講座【ストリートファイター6】【スト6】",
    "source_timestamp": "09:34",
    "source_quote": "まずは入門として強アシコンからできるものを一つ練習してみましょう。端から強アシコンを初めて下段派生までいったら22強Pで手裏剣を設置します。タイミングがつかめるまでは2を連打しながらきょうも連打する方式でも構いません。設置後は投げ連打で最速で投げる事ができコンボにすることが可能です。最速でやると有利フレームが先ほどよりもかなり長くなりこの場合は連打で投げるとスカるため投げたい場合は気持ち遅らせる必要がある点は注意が必要です。",
    "confidence": 1.0,
    "channel_trust": 0.3,
    "frame_data_conflicts": [],
    "extracted_at": "2026-03-30T07:55:03.614751",
    "game_version": "2",
    "video_upload_date": "",
    "referenced_moves": [
      "306"
    ],
    "staleness_status": "current",
    "staleness_reason": "",
    "last_validated_version": ""
  },
  {
    "id": "4059cd2458d4",
    "category": "oki",
    "topic": "手裏剣設置からのODコマ投げ派生",
    "content": "手裏剣設置後の投げ中に、9入力でジャンプしつつAuto+6SPでODコマ投げ（武神イズナ落とし）を出すことで追撃できます。ODコマ投げヒット後は6強K > ジャンプ中Pに繋ぎ、さらに22強Pで手裏剣を設置することで攻めをループさせることが可能です。",
    "characters": [
      "kimberly"
    ],
    "matchup": null,
    "situation": "手裏剣設置後",
    "source_video_id": "9kshXTikTLM",
    "source_channel": "べーやんの部屋【ゆっくり解説チャンネル】",
    "source_video_title": "【それっぽく動かすキンバリー】順番に覚えれば動画のようなセットプレイができる！ガン攻め好きにおすすめのキンバリー初心者向け解説講座【ストリートファイター6】【スト6】",
    "source_timestamp": "10:04",
    "source_quote": "投げの最中、9に入力し続けキャラがジャンプした瞬間にAuto+6SPでODコマ投げを出しましょう。ODコマ投げヒット後は6強K>J中Pから再び22強で手裏剣を設置することで攻めをループさせることができます。",
    "confidence": 1.0,
    "channel_trust": 0.3,
    "frame_data_conflicts": [],
    "extracted_at": "2026-03-30T07:55:03.614751",
    "game_version": "2",
    "video_upload_date": "",
    "referenced_moves": [
      "114",
      "318",
      "None"
    ],
    "staleness_status": "current",
    "staleness_reason": "",
    "last_validated_version": ""
  },
  {
    "id": "1d90b9c745d9",
    "category": "oki",
    "topic": "手裏剣再設置後の柔道",
    "content": "手裏剣設置後に弱Pを重ねてヒットさせると、相手の暴れや最速投げを潰す選択肢になります。相手がガードしている場合は、中段・下段の択をかけましょう。ただし、この状況は穴が多いので注意が必要です。",
    "characters": [
      "kimberly"
    ],
    "matchup": null,
    "situation": "手裏剣設置後",
    "source_video_id": "9kshXTikTLM",
    "source_channel": "べーやんの部屋【ゆっくり解説チャンネル】",
    "source_video_title": "【それっぽく動かすキンバリー】順番に覚えれば動画のようなセットプレイができる！ガン攻め好きにおすすめのキンバリー初心者向け解説講座【ストリートファイター6】【スト6】",
    "source_timestamp": "14:32",
    "source_quote": "手裏剣設置>2弱P*3>弱一文字適切な暴れや最速投げなどを入れている敵に対しての択ガードされた場合相手がおとなしくガードしているのなら中下で択をかけることもできる穴だらけなので注意",
    "confidence": 1.0,
    "channel_trust": 0.3,
    "frame_data_conflicts": [],
    "extracted_at": "2026-03-30T07:55:03.614751",
    "game_version": "2",
    "video_upload_date": "",
    "referenced_moves": [],
    "staleness_status": "current",
    "staleness_reason": "",
    "last_validated_version": ""
  },
  {
    "id": "44006e27a55b",
    "category": "oki",
    "topic": "OD疾駆けを用いたシミーからの攻め",
    "content": "OD疾駆けは自動派生にキャンセルすることで、相手の4F暴れ技を潰すことができます。OD疾駆けヒット時は蹴り派生に繋げることで壁際なら大幅有利な設置に移行できます。投げ択ヒット時も同様に追撃可能で、入れ込みでもヒットするので強Kがガードされた時点でコマンドを仕込んでおくと良いでしょう。",
    "characters": [
      "kimberly"
    ],
    "matchup": null,
    "situation": "起き攻め",
    "source_video_id": "9kshXTikTLM",
    "source_channel": "べーやんの部屋【ゆっくり解説チャンネル】",
    "source_video_title": "【それっぽく動かすキンバリー】順番に覚えれば動画のようなセットプレイができる！ガン攻め好きにおすすめのキンバリー初心者向け解説講座【ストリートファイター6】【スト6】",
    "source_timestamp": "12:43",
    "source_quote": "おすすめはOD疾駆け>自動派生へのキャンセルです。通常の疾駆けにキャンセルするとギリギリ4Fの技に割られてしまいますがOD疾駆けにキャンセルすることでこれを潰すことができます。OD疾駆けヒット時は蹴り派生することで壁際なら大幅有利の設置に行くことも可能です。投げ択ヒット時も同様に追撃が可能でとりあえず入れ込んでもヒットするので強Kがガードされた時点でコマンドを仕込んであると良いでしょう。",
    "confidence": 1.0,
    "channel_trust": 0.3,
    "frame_data_conflicts": [],
    "extracted_at": "2026-03-30T07:55:03.614751",
    "game_version": "2",
    "video_upload_date": "",
    "referenced_moves": [
      "306",
      "307"
    ],
    "staleness_status": "current",
    "staleness_reason": "",
    "last_validated_version": ""
  },
  {
    "id": "91e22562b7ac",
    "category": "oki",
    "topic": "シミー強Pからの行動（モダン）",
    "content": "モダン操作でシミーから強Pを出した後、疾駆けから派生技を出そうとするとヒットストップの関係で自動的にワープ（彩隠形）に移行しますが、問題なくコンボは可能です。後ろ下がりから強Pを出し、ヒット後に疾駆け中下段派生かワープに繋げましょう。相手がシミー後の強Pガードで中下択を迫る場合は、キンバリーが大有利なので攻めを継続できます。",
    "characters": [
      "kimberly"
    ],
    "matchup": null,
    "situation": "シミー後（モダン）",
    "source_video_id": "9kshXTikTLM",
    "source_channel": "べーやんの部屋【ゆっくり解説チャンネル】",
    "source_video_title": "【それっぽく動かすキンバリー】順番に覚えれば動画のようなセットプレイができる！ガン攻め好きにおすすめのキンバリー初心者向け解説講座【ストリートファイター6】【スト6】",
    "source_timestamp": "14:53",
    "source_quote": "シミー強Pモダンの場合疾駆けから派生を出そうとするとヒットストップの関係で自動的にワープになるその場合でも問題なくコンボは可能後ろ下がり>強P>(疾駆け中下orワープ)ガードされた場合中下で二択になるがそれをガードされたとしてもキンバリーが大有利なので攻めを継続しよう",
    "confidence": 1.0,
    "channel_trust": 0.3,
    "frame_data_conflicts": [],
    "extracted_at": "2026-03-30T07:55:03.614751",
    "game_version": "2",
    "video_upload_date": "",
    "referenced_moves": [
      "306",
      "326"
    ],
    "staleness_status": "current",
    "staleness_reason": "",
    "last_validated_version": ""
  },
  {
    "id": "eac3ea5969ef",
    "category": "oki",
    "topic": "ラッシュ5中P後の択",
    "content": "ドライブラッシュ5中Pがガードされた場合、密着で+2F有利となるため、投げと打撃の二択を仕掛けることができます。",
    "characters": [
      "kimberly"
    ],
    "matchup": null,
    "situation": "ドライブラッシュ5中Pガード時",
    "source_video_id": "SQ-0zRY2IDM",
    "source_channel": "でりちゃんねる",
    "source_video_title": "【初心者向け解説】キンバリー脱初心者10の心得 #スト6 #キンバリー #コンボ",
    "source_timestamp": "3:47",
    "source_quote": "ガード時密着＋2Fだから投げと打撃で択が揺れ～！",
    "confidence": 1.0,
    "channel_trust": 0.3,
    "frame_data_conflicts": [],
    "extracted_at": "2026-03-30T10:46:53.128209",
    "game_version": "2",
    "video_upload_date": "",
    "referenced_moves": [
      "606"
    ],
    "staleness_status": "current",
    "staleness_reason": "",
    "last_validated_version": ""
  },
  {
    "id": "fa61eb6647c0",
    "category": "oki",
    "topic": "影すくいからの起き攻め",
    "content": "影すくい（236中K）でコンボを締めた後は、前ステップを2回入力し、投げと5強Kで二択を仕掛けましょう。",
    "characters": [
      "kimberly"
    ],
    "matchup": null,
    "situation": "影すくい後の起き攻め",
    "source_video_id": "SQ-0zRY2IDM",
    "source_channel": "でりちゃんねる",
    "source_video_title": "【初心者向け解説】キンバリー脱初心者10の心得 #スト6 #キンバリー #コンボ",
    "source_timestamp": "6:58",
    "source_quote": "その後は前ステ×2から投げと5強Kで択で揺れ～！",
    "confidence": 1.0,
    "channel_trust": 0.3,
    "frame_data_conflicts": [],
    "extracted_at": "2026-03-30T10:46:53.128209",
    "game_version": "2",
    "video_upload_date": "",
    "referenced_moves": [
      "312"
    ],
    "staleness_status": "current",
    "staleness_reason": "",
    "last_validated_version": ""
  },
  {
    "id": "903e27adfa6f",
    "category": "oki",
    "topic": "投げ・SA3後のセットプレイ",
    "content": "投げやSA3後は、事前に決めておいた行動（セットプレイ）を繰り返し行うことで、より有利な状況を作り出せます。",
    "characters": [
      "kimberly"
    ],
    "matchup": null,
    "situation": "投げ/SA3後",
    "source_video_id": "SQ-0zRY2IDM",
    "source_channel": "でりちゃんねる",
    "source_video_title": "【初心者向け解説】キンバリー脱初心者10の心得 #スト6 #キンバリー #コンボ",
    "source_timestamp": "8:33",
    "source_quote": "よくある状況として、投げやSA3後のセットプレイは覚えてほしいぜ～！",
    "confidence": 1.0,
    "channel_trust": 0.3,
    "frame_data_conflicts": [],
    "extracted_at": "2026-03-30T10:46:53.128209",
    "game_version": "2",
    "video_upload_date": "",
    "referenced_moves": [],
    "staleness_status": "current",
    "staleness_reason": "",
    "last_validated_version": ""
  },
  {
    "id": "47ba6d7ba6b2",
    "category": "oki",
    "topic": "細工手裏剣（爆弾）の設置と攻め",
    "content": "細工手裏剣（爆弾）は、主に画面端で虎連牙（中P→強P）から影すくい（236中K）で締めた後に設置し、投げと打撃の二択で起き攻めを行い、コンボに繋げましょう。",
    "characters": [
      "kimberly"
    ],
    "matchup": null,
    "situation": "画面端、コンボ締め後",
    "source_video_id": "SQ-0zRY2IDM",
    "source_channel": "でりちゃんねる",
    "source_video_title": "【初心者向け解説】キンバリー脱初心者10の心得 #スト6 #キンバリー #コンボ",
    "source_timestamp": "9:42",
    "source_quote": "基本的には端で虎連牙→影すくいを決めたい後に使うぜ～！設置後は投げと打撃の択からコンボにいけ～！",
    "confidence": 1.0,
    "channel_trust": 0.3,
    "frame_data_conflicts": [],
    "extracted_at": "2026-03-30T10:46:53.128209",
    "game_version": "2",
    "video_upload_date": "",
    "referenced_moves": [
      "312",
      "606"
    ],
    "staleness_status": "current",
    "staleness_reason": "",
    "last_validated_version": ""
  },
  {
    "id": "ca98bf14518c",
    "category": "oki",
    "topic": "細工手裏剣からの打撃ガード後",
    "content": "細工手裏剣（爆弾）設置後の打撃択がガードされても、キンバリーは大幅有利なため、再度5強Kで攻めを継続できます。",
    "characters": [
      "kimberly"
    ],
    "matchup": null,
    "situation": "細工手裏剣後の打撃ガード時",
    "source_video_id": "SQ-0zRY2IDM",
    "source_channel": "でりちゃんねる",
    "source_video_title": "【初心者向け解説】キンバリー脱初心者10の心得 #スト6 #キンバリー #コンボ",
    "source_timestamp": "10:50",
    "source_quote": "打撃択はガードされても大幅有利だから5強Kでまた択れるぜ～！",
    "confidence": 1.0,
    "channel_trust": 0.3,
    "frame_data_conflicts": [],
    "extracted_at": "2026-03-30T10:46:53.128209",
    "game_version": "2",
    "video_upload_date": "",
    "referenced_moves": [
      "606"
    ],
    "staleness_status": "current",
    "staleness_reason": "",
    "last_validated_version": ""
  },
  {
    "id": "c728a8da1cd4",
    "category": "oki",
    "topic": "起き攻めでの様子見",
    "content": "起き攻めでは、ただ攻めるだけでなく、様子見の行動も混ぜて相手がパナし（無敵技）を出すのを待ち、それを咎める準備をしましょう。",
    "characters": [
      "kimberly"
    ],
    "matchup": null,
    "situation": "起き攻め時",
    "source_video_id": "SQ-0zRY2IDM",
    "source_channel": "でりちゃんねる",
    "source_video_title": "【初心者向け解説】キンバリー脱初心者10の心得 #スト6 #キンバリー #コンボ",
    "source_timestamp": "11:29",
    "source_quote": "起き攻めて様子見を混ぜて相手の自爆を待つんだぜ～！",
    "confidence": 1.0,
    "channel_trust": 0.3,
    "frame_data_conflicts": [],
    "extracted_at": "2026-03-30T10:46:53.128209",
    "game_version": "2",
    "video_upload_date": "",
    "referenced_moves": [],
    "staleness_status": "current",
    "staleness_reason": "",
    "last_validated_version": ""
  },
  {
    "id": "8f7e88f304f0",
    "category": "oki",
    "topic": "OD霧隠の積極的な活用",
    "content": "キンバリーのOD霧隠（ODドライブラッシュ）は、ヒット・ガード問わず有利な状況を作り出すことができます。ガードされてもリターンが大きいため、積極的に使って相手に攻めを押し付けましょう。OD霧隠から下段攻撃や投げの2択を仕掛けることができます。",
    "characters": [
      "kimberly"
    ],
    "matchup": null,
    "situation": null,
    "source_video_id": "b3tC7T-7_XI",
    "source_channel": "でりちゃんねる",
    "source_video_title": "【初心者向け解説】キンバリーで勝つためのコンボ諸々12の心得",
    "source_timestamp": "02:32",
    "source_quote": "逆にODドロンはリターンが大きくて、ガードされても有利だからドンドン使おう！",
    "confidence": 1.0,
    "channel_trust": 0.3,
    "frame_data_conflicts": [],
    "extracted_at": "2026-03-30T11:57:27.532391",
    "game_version": "2",
    "video_upload_date": "",
    "referenced_moves": [],
    "staleness_status": "current",
    "staleness_reason": "",
    "last_validated_version": ""
  },
  {
    "id": "afa0c570b090",
    "category": "oki",
    "topic": "相手の無敵技を警戒した起き攻め",
    "content": "初心者帯の相手は特に無敵技に頼りがちな傾向があるため、ダウンさせた後は様子見を多く取り入れるのが有効です。後ろ下がり（バックステップ）を使うことで、無敵技と投げ抜けの両方をケアしつつ、相手の隙を誘う「シミー」と呼ばれる行動が可能です。相手の無敵技が空振った際には、立ち強Pでパニッシュカウンターを狙うことができます。",
    "characters": [
      "kimberly"
    ],
    "matchup": null,
    "situation": "ダウン後の起き攻め",
    "source_video_id": "b3tC7T-7_XI",
    "source_channel": "でりちゃんねる",
    "source_video_title": "【初心者向け解説】キンバリーで勝つためのコンボ諸々12の心得",
    "source_timestamp": "03:20",
    "source_quote": "特に初心者は無敵技に頼りがちだから、ダウン後に様子見を多めにするのもアリだよね！後ろ下がりしておくと無敵技と投げ抜けの両方をケアできるよ！これってアレだよね…シミー！ここで後ろ下がり！ちょっと待って5強Pを置こう！",
    "confidence": 1.0,
    "channel_trust": 0.3,
    "frame_data_conflicts": [],
    "extracted_at": "2026-03-30T11:57:27.532391",
    "game_version": "2",
    "video_upload_date": "",
    "referenced_moves": [
      "104"
    ],
    "staleness_status": "current",
    "staleness_reason": "",
    "last_validated_version": ""
  },
  {
    "id": "3251826e78fb",
    "category": "oki",
    "topic": "画面端での細工手裏剣と二択",
    "content": "キンバリーは画面端でコンボを細工手裏剣（影すくい）に繋げることで、強力な起き攻めを展開できます。細工手裏剣で設置された爆弾は、打撃と投げの二択を相手に迫るキンバリーの最も強力な行動の一つです。爆弾を設置した後、しゃがみ弱Pで下段を狙うか、投げを仕掛けることで、相手はガードか投げ抜けかの難しい選択を迫られます。",
    "characters": [
      "kimberly"
    ],
    "matchup": null,
    "situation": "画面端での起き攻め",
    "source_video_id": "b3tC7T-7_XI",
    "source_channel": "でりちゃんねる",
    "source_video_title": "【初心者向け解説】キンバリーで勝つためのコンボ諸々12の心得",
    "source_timestamp": "04:50",
    "source_quote": "画面端のコンボは影すくいに繋げよう！ここから細工手裏剣を設置して、投げと打撃の二択を迫るんだ！細工手裏剣の起き攻めは、忍者の人の一番強い行動だよ！",
    "confidence": 1.0,
    "channel_trust": 0.3,
    "frame_data_conflicts": [],
    "extracted_at": "2026-03-30T11:57:27.532391",
    "game_version": "2",
    "video_upload_date": "",
    "referenced_moves": [
      "106",
      "312",
      "606"
    ],
    "staleness_status": "current",
    "staleness_reason": "",
    "last_validated_version": ""
  },
  {
    "id": "c0555db42a4a",
    "category": "oki",
    "topic": "中P大Pタゲコンからの起き攻め",
    "content": "中P大Pタゲコンから影すくい、最速前ダッシュ、そして首狩りに繋ぐ連携において、首狩りの部分を疾駆け急停止に変えることで、ヒット後に+7Fの有利フレームを取ることができます。この+7Fからしゃがみ中Kを出すと持続当てになり、中P大Pタゲコンまで繋がります。また、+7Fから投げも有効です。OD無敵技を持たない相手には特に強力な連携です。",
    "characters": [
      "kimberly"
    ],
    "matchup": null,
    "situation": "中P大Pタゲコンからの影すくい、最速前ダッシュ後",
    "source_video_id": "4oLHybYVIqY",
    "source_channel": "ぴんぴゲームチャンネル",
    "source_video_title": "【スト6】キンバリーでマスターになってからに覚えたコンボ・セットプレイ・起き攻め　【攻略】【ストリートファイター6】",
    "source_timestamp": "01:56",
    "source_quote": "中P大Pタゲコン→影すくい→最速前ダッシュ→首狩り。これなんですけどこの首狩りの部分を急停止します。これ見て貰うと分かると思うんですけど硬直差７F。最速でやると硬直差7Fになるんですけどこの状態で屈中Kを撃つと当たった時に持続当てになるんですね。なんでこの中P大Pタゲコンが中足から繋がる！通常は繋がらないんですけどこの中足が持続当てになってることによってこの中P大Pタゲコンが繋がります！これめちゃくちゃ当たります。2回連続で影すくい当てるこんな感じになるんで急停止からの投げも有効的。こっからの投げも見せておくと相手がね結構投げ抜けなんかをして中足が引っかかってくれたりするんで",
    "confidence": 1.0,
    "channel_trust": 0.3,
    "frame_data_conflicts": [],
    "extracted_at": "2026-03-30T14:06:23.729575",
    "game_version": "2",
    "video_upload_date": "",
    "referenced_moves": [
      "109",
      "306",
      "308",
      "312",
      "314",
      "None"
    ],
    "staleness_status": "current",
    "staleness_reason": "",
    "last_validated_version": ""
  },
  {
    "id": "cc6d0ee5acef",
    "category": "oki",
    "topic": "孤空武神穿刃脚からのラッシュ水切り蹴り連携",
    "content": "弧空→武神穿刃脚→ラッシュ水切り蹴りの連携は、ヒット時に+10Fの有利フレームが得られ、ここからしゃがみ大Pや疾駆けからの投げに繋ぐことができます。ガードされても+4F有利なので、大幅に有利な状況を作れます。OD無敵技を持たないキャラクターに対して特に有効です。",
    "characters": [
      "kimberly"
    ],
    "matchup": null,
    "situation": "孤空→武神穿刃脚後",
    "source_video_id": "4oLHybYVIqY",
    "source_channel": "ぴんぴゲームチャンネル",
    "source_video_title": "【スト6】キンバリーでマスターになってからに覚えたコンボ・セットプレイ・起き攻め　【攻略】【ストリートファイター6】",
    "source_timestamp": "03:29",
    "source_quote": "孤空→武神穿刃脚→ラッシュ水切り蹴り。これねヒットでプラス10フレーム取れます。なんでこれヒットするとこのまた中P大Pタゲコン行けますし。大Pからのねコンボにも持っていくことができます。これガードされてもプラス4フレ有利なんで、ここね大幅有利な状況を取れるんで。この後仕込み投げにも行けますし、そのままね投げちゃうこともできます。OD無敵無いキャラには特に強いです。",
    "confidence": 1.0,
    "channel_trust": 0.3,
    "frame_data_conflicts": [],
    "extracted_at": "2026-03-30T14:06:23.729575",
    "game_version": "2",
    "video_upload_date": "",
    "referenced_moves": [
      "200",
      "306",
      "316"
    ],
    "staleness_status": "current",
    "staleness_reason": "",
    "last_validated_version": ""
  },
  {
    "id": "3bdbe60fb9d6",
    "category": "oki",
    "topic": "画面端でのちょい下がり屈中P→弱一文字",
    "content": "相手が画面端でOD昇竜拳などの無敵技を警戒してくる状況で、ちょい下がり屈中P→弱一文字をセットプレイとして使用します。ちょい下がりで相手のOD昇竜拳をガードしつつ、投げ抜けを狙う相手には屈中Pがヒットし、何もしてこない相手には弱一文字がヒットします。これを一度見せれば相手は無敵技や投げ抜けを出しにくくなり、インパクトや投げが通りやすくなります。",
    "characters": [
      "kimberly"
    ],
    "matchup": null,
    "situation": "画面端での相手への固め、特にOD無敵技を警戒する時",
    "source_video_id": "4oLHybYVIqY",
    "source_channel": "ぴんぴゲームチャンネル",
    "source_video_title": "【スト6】キンバリーでマスターになってからに覚えたコンボ・セットプレイ・起き攻め　【攻略】【ストリートファイター6】",
    "source_timestamp": "06:02",
    "source_quote": "画面端のスプレーのセットプレイなんですけど、前回の動画でね、画面端のね、スプレーのセットプレイを紹介したんですけど、これだけでいいやって思うのが一つ合って。これねプロゲーマーの方とかねよく使ってるんですけど。ODからちょい下がり屈中P→弱一文字。これね相手OD昇竜拳ぶっぱなしてきたらガードできるし、相手が投げ抜けをしてたら投げ抜けに中Pが刺さるし。そのままスプレーので爆発まで持ってけれるんで。これめちゃくちゃ使えます本当に。これね1回見せるとね、もうあまりぶっぱなしもしてこなくなるし、投げ抜けもせずらくなるんでこうなったらね、もうガンガードとかね、パリーしてくることが多くなるんで。そしたらこうやってなんかインパクト撃ってみたり。投げが通りやすくなる。そうすると投げが通ったりするんですよ。このちょい下がりしゃがみ中パンチ弱一文字。これめちゃくちゃ使えます本当に。",
    "confidence": 1.0,
    "channel_trust": 0.3,
    "frame_data_conflicts": [],
    "extracted_at": "2026-03-30T14:06:23.729575",
    "game_version": "2",
    "video_upload_date": "",
    "referenced_moves": [
      "102"
    ],
    "staleness_status": "current",
    "staleness_reason": "",
    "last_validated_version": ""
  },
  {
    "id": "bf4129dd65f8",
    "category": "oki",
    "topic": "バーンアウト時の強力なループ連携",
    "content": "相手がバーンアウト中の場合、しゃがみ強P→疾駆けの強K派生が非常に強力です。ヒットしたら最速前ダッシュで+5F有利となり、そこから再度しゃがみ強P→疾駆けの強K派生をループさせることができます。この連携は知らない相手には永遠にヒットし続ける可能性があり、高いダメージが期待できます。ただし、相手にSAが溜まっている場合は注意が必要です。",
    "characters": [
      "kimberly"
    ],
    "matchup": null,
    "situation": "相手がバーンアウト中の時",
    "source_video_id": "4oLHybYVIqY",
    "source_channel": "ぴんぴゲームチャンネル",
    "source_video_title": "【スト6】キンバリーでマスターになってからに覚えたコンボ・セットプレイ・起き攻め　【攻略】【ストリートファイター6】",
    "source_timestamp": "07:56",
    "source_quote": "相手がね、バーンアウトした時に取ると強い行動をね紹介していきたいと思います。相手がバーンアウトしたとして、しゃがみ強P→首狩り。これねガードされて、えー、プラス1フレなんですけど。これがヒットした場合。ヒット後前ダッシュで+5。また有利フレーム+5Fなんです最速前ダッシュすると。また最速前ダッシュしたらまたしゃがみ強P→中断。これ延々に行けますヒットしてたら。もちろんこれ相手にSAがある時は注意。たまにこうやって連続で中断打ったりとか。これ抜け出せる人なかなかいないです。これ知らない人延々こうやって食らってくれるんで。これであのバーンアウトした相手をね、そのままKOしたこともね何回もあるんで。これね是非練習しておいてください。これ本当に相手バーンアウトした時にやると面白いぐらい当たるんで。",
    "confidence": 1.0,
    "channel_trust": 0.3,
    "frame_data_conflicts": [],
    "extracted_at": "2026-03-30T14:06:23.729575",
    "game_version": "2",
    "video_upload_date": "",
    "referenced_moves": [
      "110",
      "306",
      "314"
    ],
    "staleness_status": "current",
    "staleness_reason": "",
    "last_validated_version": ""
  },
  {
    "id": "ff003b251370",
    "category": "oki",
    "topic": "OD空中投げ後の詐欺飛び",
    "content": "キンバリーのOD空中投げで相手をダウンさせると、+42Fの状況となり、立ち強Kからのジャンプ強Pで詐欺飛びにできる。",
    "characters": [
      "kimberly"
    ],
    "matchup": null,
    "situation": "OD空中投げ後",
    "source_video_id": "3CdPbRniC-A",
    "source_channel": "トマソン#スト6委員会",
    "source_video_title": "【スト6】キンバリーのコンボは3つ覚えればOK【キンバリー解説】",
    "source_timestamp": "00:07",
    "source_quote": "OD空投げ→6強K→ジャンプ強Pで+42F",
    "confidence": 1.0,
    "channel_trust": 0.3,
    "frame_data_conflicts": [],
    "extracted_at": "2026-03-30T23:26:02.274374",
    "game_version": "2",
    "video_upload_date": "",
    "referenced_moves": [
      "105",
      "116"
    ],
    "staleness_status": "current",
    "staleness_reason": "",
    "last_validated_version": ""
  },
  {
    "id": "04a664769ef6",
    "category": "oki",
    "topic": "投げからの爆弾起き攻め",
    "content": "キンバリーが投げで相手をダウンさせた後、鉄火爆を設置し、爆発と同時に空中投げを狙う起き攻め連携が有効である。",
    "characters": [
      "kimberly"
    ],
    "matchup": null,
    "situation": "相手を投げた後",
    "source_video_id": "3CdPbRniC-A",
    "source_channel": "トマソン#スト6委員会",
    "source_video_title": "【スト6】キンバリーのコンボは3つ覚えればOK【キンバリー解説】",
    "source_timestamp": "00:49",
    "source_quote": "投げ→爆発→空投げ",
    "confidence": 1.0,
    "channel_trust": 0.3,
    "frame_data_conflicts": [],
    "extracted_at": "2026-03-30T23:26:02.274374",
    "game_version": "2",
    "video_upload_date": "",
    "referenced_moves": [],
    "staleness_status": "current",
    "staleness_reason": "",
    "last_validated_version": ""
  },
  {
    "id": "d2f364197c32",
    "category": "oki",
    "topic": "立ち強Kからのめくり",
    "content": "キンバリーの立ち強Kは、相手の裏に回り込んで攻撃するめくり技として起き攻めに有効である。",
    "characters": [
      "kimberly"
    ],
    "matchup": null,
    "situation": "相手ダウン時、画面端付近",
    "source_video_id": "3CdPbRniC-A",
    "source_channel": "トマソン#スト6委員会",
    "source_video_title": "【スト6】キンバリーのコンボは3つ覚えればOK【キンバリー解説】",
    "source_timestamp": "01:22",
    "source_quote": "6強Kからのめくりがオヌヌメ",
    "confidence": 1.0,
    "channel_trust": 0.3,
    "frame_data_conflicts": [],
    "extracted_at": "2026-03-30T23:26:02.274374",
    "game_version": "2",
    "video_upload_date": "",
    "referenced_moves": [
      "105"
    ],
    "staleness_status": "current",
    "staleness_reason": "",
    "last_validated_version": ""
  },
  {
    "id": "7fd5609b9f86",
    "category": "oki",
    "topic": "画面端での起き攻めループ",
    "content": "キンバリーは画面端で相手をダウンさせた後、投げと弱流転を交互に使うことで起き攻めを継続できる。",
    "characters": [
      "kimberly"
    ],
    "matchup": null,
    "situation": "画面端、相手ダウン時",
    "source_video_id": "3CdPbRniC-A",
    "source_channel": "トマソン#スト6委員会",
    "source_video_title": "【スト6】キンバリーのコンボは3つ覚えればOK【キンバリー解説】",
    "source_timestamp": "01:29",
    "source_quote": "端は投げと弱流転ループ",
    "confidence": 1.0,
    "channel_trust": 0.3,
    "frame_data_conflicts": [],
    "extracted_at": "2026-03-30T23:26:02.274374",
    "game_version": "2",
    "video_upload_date": "",
    "referenced_moves": [
      "604"
    ],
    "staleness_status": "current",
    "staleness_reason": "",
    "last_validated_version": ""
  },
  {
    "id": "4b0de43db8d6",
    "category": "oki",
    "topic": "弱攻撃始動の起き攻め",
    "content": "キンバリーの弱攻撃始動コンボ（コパン>コパン>弱流転一文字）後、相手をダウンさせると投げ間合い+3Fの状態になる。この時、投げを選択するか、しゃがみ中パンでシミー（暴れ潰し）を狙うことが可能。打撃択に行くならしゃがみ中パンが最適。",
    "characters": [
      "kimberly"
    ],
    "matchup": null,
    "situation": "弱攻撃始動コンボ後",
    "source_video_id": "sVBQ0-fQImQ",
    "source_channel": "なお",
    "source_video_title": "キンバリーの基本コンボと起き攻めを紹介！【スト6】",
    "source_timestamp": "00:22",
    "source_quote": "基本はコパンから弱流転一文字に繋げます。コンボ終了後はシミー可能な投げ間合い+3F。シミーするときはしゃがみ中パンを使うと楽です。打撃択に行くならしゃがみ中パンが最適です。",
    "confidence": 1.0,
    "channel_trust": 0.3,
    "frame_data_conflicts": [],
    "extracted_at": "2026-03-31T00:35:38.830240",
    "game_version": "2",
    "video_upload_date": "",
    "referenced_moves": [
      "100",
      "102",
      "322",
      "604",
      "606"
    ],
    "staleness_status": "current",
    "staleness_reason": "",
    "last_validated_version": ""
  },
  {
    "id": "124fab5365c7",
    "category": "oki",
    "topic": "弱攻撃始動（画面端）の起き攻め",
    "content": "キンバリーの弱攻撃始動コンボ（コパン>コパン>強武神旋風脚）を画面端で決めた場合、密着状態となるため起き攻めが可能。一応引き大Kは安定して重ねられる。",
    "characters": [
      "kimberly"
    ],
    "matchup": null,
    "situation": "弱攻撃始動コンボ（画面端）後",
    "source_video_id": "sVBQ0-fQImQ",
    "source_channel": "なお",
    "source_video_title": "キンバリーの基本コンボと起き攻めを紹介！【スト6】",
    "source_timestamp": "01:00",
    "source_quote": "画面端なら当然密着なので起き攻めできます。ただし、フレームが結構変動するので固定のセットプレイを組むのは難しいです。一応引き大Kは安定して重なります。",
    "confidence": 1.0,
    "channel_trust": 0.3,
    "frame_data_conflicts": [],
    "extracted_at": "2026-03-31T00:35:38.830240",
    "game_version": "2",
    "video_upload_date": "",
    "referenced_moves": [
      "100",
      "105",
      "302"
    ],
    "staleness_status": "current",
    "staleness_reason": "",
    "last_validated_version": ""
  },
  {
    "id": "95b2215d363f",
    "category": "oki",
    "topic": "疾駆けからの起き攻め連携（簡単択）",
    "content": "キンバリーの疾駆けからの起き攻めとして、最も簡単なのは最速首狩り派生。ガード時には持続重ねで+1F有利が取れる。ヒット時は前ステップから起き攻めできるが、後ろ受け身されると投げを避けられる可能性があるので注意。ガード時はコパン中パン連携で暴れ潰しを狙える。",
    "characters": [
      "kimberly"
    ],
    "matchup": null,
    "situation": "疾駆け後",
    "source_video_id": "sVBQ0-fQImQ",
    "source_channel": "なお",
    "source_video_title": "キンバリーの基本コンボと起き攻めを紹介！【スト6】",
    "source_timestamp": "01:57",
    "source_quote": "一番簡単なのは最速首狩り派生です。首狩りが持続重ねになり、ガードされても有利になります。ヒットしていた場合は前ステから起き攻め。ただし、後ろ受け身されると後ろ歩きで投げを避けられます。ガードされていた場合はコパン中パンと連携を組むことで暴れ潰しからリターンを取れます。",
    "confidence": 1.0,
    "channel_trust": 0.3,
    "frame_data_conflicts": [],
    "extracted_at": "2026-03-31T00:35:38.830240",
    "game_version": "2",
    "video_upload_date": "",
    "referenced_moves": [
      "100",
      "102",
      "306",
      "314"
    ],
    "staleness_status": "current",
    "staleness_reason": "",
    "last_validated_version": ""
  },
  {
    "id": "6c74532f6d4f",
    "category": "oki",
    "topic": "疾駆けからの起き攻め連携（急停止択）",
    "content": "キンバリーの疾駆けから急停止して投げを狙う起き攻め。最速で停止すると移動距離が足りないので、目押しで少し遅らせて停止する必要がある。この起き攻めは、その場起きに対してシミーができない。疾駆け急停止から中足も有効な下段択で、投げと同じく少し遅らせて停止する必要がある。",
    "characters": [
      "kimberly"
    ],
    "matchup": null,
    "situation": "疾駆け後",
    "source_video_id": "sVBQ0-fQImQ",
    "source_channel": "なお",
    "source_video_title": "キンバリーの基本コンボと起き攻めを紹介！【スト6】",
    "source_timestamp": "02:17",
    "source_quote": "次に疾駆けから急停止して投げ。最速で停止すると移動距離が足りないため、目押しで少し遅らせて停止しましょう。また、この起き攻めはその場起きに対してシミーができないです。最後に疾駆け急停止から中足。最初の首狩り持続重ねの対の下段択です。こちらも投げと同じく少し遅らせて停止する必要があります。",
    "confidence": 1.0,
    "channel_trust": 0.3,
    "frame_data_conflicts": [],
    "extracted_at": "2026-03-31T00:35:38.830240",
    "game_version": "2",
    "video_upload_date": "",
    "referenced_moves": [
      "109",
      "306",
      "308",
      "314"
    ],
    "staleness_status": "current",
    "staleness_reason": "",
    "last_validated_version": ""
  },
  {
    "id": "549a6658da7e",
    "category": "oki",
    "topic": "生ラッシュからの起き攻め連携",
    "content": "キンバリーは生ラッシュを使った起き攻めも可能。最速で引き大Kを出すと中段択、最速で中Kを出すと下段択となる。生ラッシュ後何も行動しないと投げられるため、シミーを狙う場合はコパンで止める必要がある。",
    "characters": [
      "kimberly"
    ],
    "matchup": null,
    "situation": "生ラッシュ後",
    "source_video_id": "sVBQ0-fQImQ",
    "source_channel": "なお",
    "source_video_title": "キンバリーの基本コンボと起き攻めを紹介！【スト6】",
    "source_timestamp": "02:51",
    "source_quote": "また、生ラッシュを使って起き攻めすることもできます。この場合は最速引き大Kで中段択。最速中Kで下段択になります。生ラッシュから何も動しないと普通に投げられます。シミーしたい場合はコパンで止まる必要があります。",
    "confidence": 1.0,
    "channel_trust": 0.3,
    "frame_data_conflicts": [],
    "extracted_at": "2026-03-31T00:35:38.830240",
    "game_version": "2",
    "video_upload_date": "",
    "referenced_moves": [
      "100",
      "105"
    ],
    "staleness_status": "current",
    "staleness_reason": "",
    "last_validated_version": ""
  },
  {
    "id": "036daef8b161",
    "category": "oki",
    "topic": "弱武神旋風脚締めからの+8F起き攻め",
    "content": "キンバリーが弱武神旋風脚でダウンを奪った後、コパンを空振ることで+8Fを作れる。この+8Fから中足を出すと持続重ねになり、ヒット時は+7Fからしゃがみ中パンに繋げる。中足持続重ねはDリバーサルを誘発させることができ、OD無敵を持たないキャラには積極的に使いたい。また、ガード時には+3F有利が取れるため、しゃがみ中パンで暴れ潰しが可能。投げは間合いではないので、少し歩く必要がある。",
    "characters": [
      "kimberly"
    ],
    "matchup": null,
    "situation": "弱武神旋風脚締め後",
    "source_video_id": "sVBQ0-fQImQ",
    "source_channel": "なお",
    "source_video_title": "キンバリーの基本コンボと起き攻めを紹介！【スト6】",
    "source_timestamp": "03:37",
    "source_quote": "コパンを空振ると+8Fを作れるのですが、ここから中足を出ることで中足持続重ねができます。こうすることでヒット時+7Fを取れ、しゃがみ中パンを繋げることができます。また、中足持続重ねだとDリバを誘発することができます。OD無敵がないキャラには積極的に使いたいです。また、ガード時+3Fを取れるので、しゃがみ中パンで暴れ潰しができます。流石に投げ間合いではないので投げに行くときは少し歩きましょう。",
    "confidence": 1.0,
    "channel_trust": 0.3,
    "frame_data_conflicts": [],
    "extracted_at": "2026-03-31T00:35:38.830240",
    "game_version": "2",
    "video_upload_date": "",
    "referenced_moves": [
      "100",
      "102",
      "109",
      "300",
      "None"
    ],
    "staleness_status": "current",
    "staleness_reason": "",
    "last_validated_version": ""
  },
  {
    "id": "51b87b3f4155",
    "category": "oki",
    "topic": "弱武神旋風脚締めからの+8F起き攻め（中段択）",
    "content": "キンバリーが弱武神旋風脚でダウンを奪った後、コパンを空振りして+8Fを作り、そこから引き大Kを出すことで中段択となる。ただし、相手に読まれているとガードされやすいので、リーサルを狙える時など温存して使うのが良い。",
    "characters": [
      "kimberly"
    ],
    "matchup": null,
    "situation": "弱武神旋風脚締め後",
    "source_video_id": "sVBQ0-fQImQ",
    "source_channel": "なお",
    "source_video_title": "キンバリーの基本コンボと起き攻めを紹介！【スト6】",
    "source_timestamp": "04:23",
    "source_quote": "先ほどの中足の対の中段択として使います。バレてると結構ガードされます。ですので基本的には温存しておいてリーサルの時に急に出すのがいいと思います。",
    "confidence": 1.0,
    "channel_trust": 0.3,
    "frame_data_conflicts": [],
    "extracted_at": "2026-03-31T00:35:38.830240",
    "game_version": "2",
    "video_upload_date": "",
    "referenced_moves": [
      "100",
      "105",
      "109",
      "300",
      "None"
    ],
    "staleness_status": "current",
    "staleness_reason": "",
    "last_validated_version": ""
  },
  {
    "id": "2598e183eef9",
    "category": "oki",
    "topic": "弱武神旋風脚締めからの+8F起き攻め（ジャスパ警戒択）",
    "content": "キンバリーが弱武神旋風脚でダウンを奪った後、コパンを空振りして+8Fを作り、そこから投げを狙うと、ジャストパリィ警戒の打撃択となる。コパン空振りで+8Fを作っているため、投げは目押しで遅らせる必要がある。しかし、コパンを空振ると相手の最速投げを下がれない場合があるので、空振らない方が良い可能性がある。2F以上遅らせて投げれば投げシミーとして成立する。",
    "characters": [
      "kimberly"
    ],
    "matchup": null,
    "situation": "弱武神旋風脚締め後",
    "source_video_id": "sVBQ0-fQImQ",
    "source_channel": "なお",
    "source_video_title": "キンバリーの基本コンボと起き攻めを紹介！【スト6】",
    "source_timestamp": "04:57",
    "source_quote": "要するにジャスパ警戒の打撃択です。最後にコパン空振り投げ。コパン空振りで+8Fを作っているので、投げは目押しで遅らせる必要があります。実はコパンを空振ると相手の最速投げを下がれないので、コパンを空振らない方がいい可能性があります。2F以上遅らせると投げを下げれるので実質では投げシミーとしてが成立します。",
    "confidence": 1.0,
    "channel_trust": 0.3,
    "frame_data_conflicts": [],
    "extracted_at": "2026-03-31T00:35:38.830240",
    "game_version": "2",
    "video_upload_date": "",
    "referenced_moves": [
      "100",
      "300",
      "606",
      "607",
      "None"
    ],
    "staleness_status": "current",
    "staleness_reason": "",
    "last_validated_version": ""
  },
  {
    "id": "edec4a7ef6ee",
    "category": "oki",
    "topic": "中K/中P始動コンボ後の起き攻め",
    "content": "キンバリーの立ち回りの中Kや暴れ潰しの中Pなどから、中Kor中P>疾駆け>武神旋風脚と繋ぐコンボ。画面中央だとコンボ後の有利フレームは+30Fで、これは中大TCからの武神旋風脚と同じ。そのため、起き攻めはそちらの流用が可能。コンボ終了時に常に画面中央に到達する場合、疾駆け急停止で密着+8Fを作れる。ただし、相手が完全に画面端にいる場合は+29Fとなり、有利フレームが1F減る。この場合はしゃがみ中パンを空振ることで+8Fを作ることができる。",
    "characters": [
      "kimberly"
    ],
    "matchup": null,
    "situation": null,
    "source_video_id": "sVBQ0-fQImQ",
    "source_channel": "なお",
    "source_video_title": "キンバリーの基本コンボと起き攻めを紹介！【スト6】",
    "source_timestamp": "07:07",
    "source_quote": "これが中攻撃始動で最後に紹介するコンボです。別にメインで狙うコンボではないですが、暴れつぶしや立ち回りの強いKなど結構この状況が来ます。ですので、この後の状況をちゃんと整理しておくとひっかけた時の爆発力につながります。このコンボは完全画面端と画面中央でフレームが異なります。画面中央だと+30Fなのですが、これは中大TCからの武神旋風脚と同じフレームです。その為、起き攻めも完全に流用できます。コンボ終了時に常に到達する場合は、疾駆け急停止で密着+8Fを作れます。ただし、相手が完全に画面端にいる場合は+29Fとなり、有利フレームが1F減ります。この場合はしゃがみ中パンを空振ることで+8Fを作ることができます。",
    "confidence": 1.0,
    "channel_trust": 0.3,
    "frame_data_conflicts": [],
    "extracted_at": "2026-03-31T00:35:38.830240",
    "game_version": "2",
    "video_upload_date": "",
    "referenced_moves": [
      "102",
      "306",
      "308",
      "None"
    ],
    "staleness_status": "current",
    "staleness_reason": "",
    "last_validated_version": ""
  },
  {
    "id": "732c2899e630",
    "category": "oki",
    "topic": "強P始動（画面端）からの前ステ起き攻め",
    "content": "キンバリーの強P始動コンボを画面端で決めた後、前ステップすることで投げ間合い+4Fを作れる。この時、少し後ろに下がることで相手の投げを避けることが可能。バックステップや上入れっぱなしを読んだ場合はしゃがみ中パンを選択する。",
    "characters": [
      "kimberly"
    ],
    "matchup": null,
    "situation": "強P始動コンボ後（画面端）",
    "source_video_id": "sVBQ0-fQImQ",
    "source_channel": "なお",
    "source_video_title": "キンバリーの基本コンボと起き攻めを紹介！【スト6】",
    "source_timestamp": "09:54",
    "source_quote": "コンボ終了後に前ステすることで投げ間合い+4Fを作れます。ここでも少し後ろに下がることで相手の投げを避けることができます。個人的にここの投げはヒット率が非常に高い気がします。バクステや上入れっぱを読んだ場合はしゃがみ中パンを選択しましょう。",
    "confidence": 1.0,
    "channel_trust": 0.3,
    "frame_data_conflicts": [],
    "extracted_at": "2026-03-31T00:35:38.830240",
    "game_version": "2",
    "video_upload_date": "",
    "referenced_moves": [
      "102"
    ],
    "staleness_status": "current",
    "staleness_reason": "",
    "last_validated_version": ""
  },
  {
    "id": "14ffe2404b01",
    "category": "oki",
    "topic": "Dゲージ使用強P始動からの詐欺飛び",
    "content": "キンバリーの強P始動Dゲージ使用コンボで、強P>強流転一文字>OD流転膝斬り>前大K>ジャンプ大Pと繋ぐと詐欺飛びとなる。キンバリーでは強力な攻め展開が難しいため、Dゲージを回復したい時に使用する。ジャンプ大Pからしゃがみ大Pを振るだけでDゲージを完全に回収できる。",
    "characters": [
      "kimberly"
    ],
    "matchup": null,
    "situation": null,
    "source_video_id": "sVBQ0-fQImQ",
    "source_channel": "なお",
    "source_video_title": "キンバリーの基本コンボと起き攻めを紹介！【スト6】",
    "source_timestamp": "10:45",
    "source_quote": "ただ、このセットプレイだけ変わってきます。これは詐欺飛びのセットプレイです。キンバリーならそこまで強力な攻めを展開できないのでDゲージを回復したいときに使いましょう。ジャンプ大Pからしゃがみ大Pを振るだけで完全にDゲージ回収できます。",
    "confidence": 1.0,
    "channel_trust": 0.3,
    "frame_data_conflicts": [],
    "extracted_at": "2026-03-31T00:35:38.830240",
    "game_version": "2",
    "video_upload_date": "",
    "referenced_moves": [
      "105",
      "324",
      "604"
    ],
    "staleness_status": "current",
    "staleness_reason": "",
    "last_validated_version": ""
  },
  {
    "id": "5db6b9e390d7",
    "category": "oki",
    "topic": "投げからの設置起き攻め基本",
    "content": "キンバリーが相手を投げた後、手裏剣（爆弾）を設置し、相手の投げ間合いの外まで下がってしゃがみガードすることで、様々な相手の行動に対応しやすくなる。基本的にはこの距離での様子見が強力。",
    "characters": [
      "kimberly"
    ],
    "matchup": null,
    "situation": "投げからの起き攻め",
    "source_video_id": "4l2HtxBQFeU",
    "source_channel": "原縫あざみ",
    "source_video_title": "【スト６】キンバリー攻略・解説：最強の設置起き攻め『様子見』",
    "source_timestamp": "00:11",
    "source_quote": "相手の投げ間合いの外まで下がってしゃがみガードする",
    "confidence": 1.0,
    "channel_trust": 0.3,
    "frame_data_conflicts": [],
    "extracted_at": "2026-03-31T00:38:09.958389",
    "game_version": "2",
    "video_upload_date": "",
    "referenced_moves": [],
    "staleness_status": "current",
    "staleness_reason": "",
    "last_validated_version": ""
  },
  {
    "id": "7165ea79631c",
    "category": "oki",
    "topic": "対キャミィ画面端起き攻め",
    "content": "キンバリーが画面端でキャミィに起き攻めをする際、以下の読み合いが可能です。\n・ODキャノンスパイクや逆択しゃがみ中Kに対しては、垂直ジャンプで回避し、空振り後に立ち強K > しゃがみ中K > 立ち強K > OD武神旋風脚で反撃できます。\n・投げ抜けや逆択ODキャノンストライクに対しては、投げを狙うと有効です。投げ抜けをされた場合は、しゃがみ強P > しゃがみ中K > 立ち強K > OD武神旋風脚で反撃し、ODキャノンストライクは投げで潰すことができます。",
    "characters": [
      "kimberly",
      "cammy"
    ],
    "matchup": "cammy",
    "situation": "キャミィが画面端で起き上がる時",
    "source_video_id": "7bggzRpPLDw",
    "source_channel": "隼「スト6」",
    "source_video_title": "【キャラ対策】キンバリー視点の「キャミィ」対策【スト6】",
    "source_timestamp": "01:30",
    "source_quote": "画面端密着起き攻め 垂直ジャンプ / ODキャノンスパイク・投げ抜け・逆択屈中K・逆択ODキャノンストライク",
    "confidence": 1.0,
    "channel_trust": 0.3,
    "frame_data_conflicts": [],
    "extracted_at": "2026-03-31T01:48:45.467042",
    "game_version": "2",
    "video_upload_date": "",
    "referenced_moves": [
      "105",
      "109",
      "110",
      "303",
      "309",
      "323",
      "324"
    ],
    "staleness_status": "current",
    "staleness_reason": "",
    "last_validated_version": ""
  },
  {
    "id": "7165ea79631c",
    "category": "oki",
    "topic": "対キャミィ画面端起き攻め",
    "content": "キンバリーが画面端でキャミィに起き攻めをする際、以下の読み合いが可能です。\n・ODキャノンスパイクや逆択しゃがみ中Kに対しては、垂直ジャンプで回避し、空振り後に立ち強K > しゃがみ中K > 立ち強K > OD武神旋風脚で反撃できます。\n・投げ抜けや逆択ODキャノンストライクに対しては、投げを狙うと有効です。投げ抜けをされた場合は、しゃがみ強P > しゃがみ中K > 立ち強K > OD武神旋風脚で反撃し、ODキャノンストライクは投げで潰すことができます。",
    "characters": [
      "kimberly",
      "cammy"
    ],
    "matchup": "cammy",
    "situation": "キャミィが画面端で起き上がる時",
    "source_video_id": "7bggzRpPLDw",
    "source_channel": "隼「スト6」",
    "source_video_title": "【キャラ対策】キンバリー視点の「キャミィ」対策【スト6】",
    "source_timestamp": "01:30",
    "source_quote": "画面端密着起き攻め 垂直ジャンプ / ODキャノンスパイク・投げ抜け・逆択屈中K・逆択ODキャノンストライク",
    "confidence": 1.0,
    "channel_trust": 0.3,
    "frame_data_conflicts": [],
    "extracted_at": "2026-03-31T01:48:45.467042",
    "game_version": "2",
    "video_upload_date": "",
    "referenced_moves": [
      "105",
      "109",
      "110",
      "303",
      "309",
      "323",
      "324"
    ],
    "staleness_status": "current",
    "staleness_reason": "",
    "last_validated_version": ""
  }
]